git_dump.py
git_dump_tool-0.1.1.dist-info/LICENSE
git_dump_tool-0.1.1.dist-info/METADATA
git_dump_tool-0.1.1.dist-info/WHEEL
git_dump_tool-0.1.1.dist-info/entry_points.txt
git_dump_tool-0.1.1.dist-info/top_level.txt
git_dump_tool-0.1.1.dist-info/RECORD
