Metadata-Version: 2.1
Name: git-dump-tool
Version: 0.1.1
Author: Sergey M
License: # LICENSE
Project-URL: Repository, https://github.com/s3rgeym/git-dump.git
Classifier: Topic :: Internet
Requires-Python: >=3.6.5
License-File: LICENSE
Requires-Dist: requests
Provides-Extra: dev
Requires-Dist: black ; extra == 'dev'
Requires-Dist: pylint ; extra == 'dev'
Provides-Extra: test
Requires-Dist: pytest ; extra == 'test'
